pysaps/__init__.py
pysaps/cli.py
pysaps/issue/__init__.py
pysaps/issue/severity.py
pysaps/issue/parsers/__init__.py
pysaps/issue/parsers/clang.py
pysaps/issue/parsers/clang_tidy.py
pysaps/issue/parsers/gcc.py
pysaps/issue/parsers/gcc4.py
pysaps/issue/parsers/msvc.py
pysaps/issue/serializers/__init__.py
pysaps/issue/serializers/gitlab.py
pysaps-0.0.8.dist-info/LICENSE
pysaps-0.0.8.dist-info/METADATA
pysaps-0.0.8.dist-info/WHEEL
pysaps-0.0.8.dist-info/entry_points.txt
pysaps-0.0.8.dist-info/top_level.txt
pysaps-0.0.8.dist-info/RECORD
