Metadata-Version: 2.1
Name: pysaps
Version: 0.0.8
Summary: ysap aims to bring something akin to jenkins static analysis parsing capabilities to a python package
Home-page: https://gitlab.com/torres.soldado/python-static-analysis-parsers
Author: Sergio Torres Soldado
Author-email: hubshuffle@gmail.com
License: UNKNOWN
Project-URL: Bug Tracker, https://gitlab.com/torres.soldado/python-static-analysis-parser/-/issues
Platform: UNKNOWN
Classifier: Programming Language :: Python :: 3
Classifier: License :: OSI Approved :: MIT License
Classifier: Operating System :: OS Independent
Classifier: Environment :: Console
Classifier: Intended Audience :: Developers
Classifier: Intended Audience :: End Users/Desktop
Requires-Python: >=3.7
License-File: LICENSE
